X2021QianduanRemenJishuJiedu/README.md
X2021QianduanRemenJishuJiedu/__init__.py
X2021QianduanRemenJishuJiedu/__main__.py
X2021QianduanRemenJishuJiedu/file.pdf
X2021QianduanRemenJishuJiedu/index.html
x2021_qianduan_remen_jishu_jiedu-2024.3.6.0.dist-info/METADATA
x2021_qianduan_remen_jishu_jiedu-2024.3.6.0.dist-info/WHEEL
x2021_qianduan_remen_jishu_jiedu-2024.3.6.0.dist-info/entry_points.txt
x2021_qianduan_remen_jishu_jiedu-2024.3.6.0.dist-info/top_level.txt
x2021_qianduan_remen_jishu_jiedu-2024.3.6.0.dist-info/RECORD
